api_utils.py
nerevu_api_utils-0.0.5.dist-info/LICENSE
nerevu_api_utils-0.0.5.dist-info/METADATA
nerevu_api_utils-0.0.5.dist-info/WHEEL
nerevu_api_utils-0.0.5.dist-info/top_level.txt
nerevu_api_utils-0.0.5.dist-info/RECORD
