Metadata-Version: 2.1
Name: nerevu-api-utils
Version: 0.0.5
Summary: Flask API utility library
Home-page: https://github.com/reubano/nerevu-api-utils
Author: Reuben Cummings
Author-email: reubano@gmail.com
License: MIT
Download-URL: https://github.com/reubano/nerevu-api-utils/archive/v0.0.5.tar.gz
Keywords: nerevu-api-utils,Flask,API,utility,library
Platform: MacOS X
Platform: Windows
Platform: Linux
Classifier: License :: OSI Approved :: MIT License
Classifier: Development Status :: 2 - Pre-Alpha
Classifier: Natural Language :: English
Classifier: Programming Language :: Python :: 3
Classifier: Programming Language :: Python :: 3 :: Only
Classifier: Programming Language :: Python :: 3.7
Classifier: Programming Language :: Python :: 3.8
Classifier: Programming Language :: Python :: 3.9
Classifier: Programming Language :: Python :: Implementation :: CPython
Classifier: Programming Language :: Python :: Implementation :: PyPy
Classifier: Environment :: Console
Classifier: Topic :: Software Development :: Libraries :: Python Modules
Classifier: Intended Audience :: Developers
Classifier: Operating System :: POSIX :: Linux
Classifier: Operating System :: MacOS :: MacOS X
Classifier: Operating System :: Microsoft :: Windows
License-File: LICENSE
Requires-Dist: flask
Requires-Dist: python-dateutil (<3.0.0,>=2.8.2)
Requires-Dist: meza (<1.0.0,>=0.45.5)
Requires-Dist: SQLAlchemy (<3.0.0,>=1.2.0)
Provides-Extra: develop
Requires-Dist: pip (>20.0) ; extra == 'develop'
Requires-Dist: wheel (>=0.29.0) ; extra == 'develop'
Requires-Dist: flake8 (<5.0.0,>=3.7.9) ; extra == 'develop'
Requires-Dist: nose (<2.0.0,>=1.3.7) ; extra == 'develop'
Requires-Dist: black (<22.0,>=19.3b0) ; extra == 'develop'
Requires-Dist: flake8-black (<0.3.0,>=0.1.1) ; extra == 'develop'
Requires-Dist: coverage (<7.0.0,>=4.0.0) ; extra == 'develop'
Requires-Dist: pylint (<3.0.0,>=2.5.0) ; extra == 'develop'
Requires-Dist: tox (<4.0.0,>=3.14.3) ; extra == 'develop'
Requires-Dist: twine (<4.0.0,>=3.2.0) ; extra == 'develop'
Requires-Dist: setuptools (>=42.0.2) ; extra == 'develop'
Requires-Dist: manage.py (<0.3.0,>=0.2.10) ; extra == 'develop'
Requires-Dist: isort (<6.0.0,>=5.10.1) ; extra == 'develop'
Requires-Dist: pkutils (<4.0.0,>=3.0.0) ; extra == 'develop'
